noctua/__init__.py
noctua/_version.py
noctua/amigo.py
noctua/barista.py
noctua/cli.py
noctua/models.py
noctua/noctua_screenshots.py
noctua/session.py
noctua-0.1.2.dist-info/METADATA
noctua-0.1.2.dist-info/WHEEL
noctua-0.1.2.dist-info/entry_points.txt
noctua-0.1.2.dist-info/licenses/LICENSE
noctua-0.1.2.dist-info/RECORD
