Metadata-Version: 2.4
Name: noctua
Version: 0.1.2
Summary: TODO
Author-email: My Name <my-name@my-org.org>
License-Expression: BSD-3-Clause
License-File: LICENSE
Requires-Python: <4.0,>=3.10
Requires-Dist: gocam>=0.5.2
Requires-Dist: httpx>=0.27.0
Requires-Dist: linkml-runtime>=1.9.4
Requires-Dist: linkml-store>=0.2.11
Requires-Dist: numpy>=2.2.6
Requires-Dist: pandas>=2.3.3
Requires-Dist: pyyaml>=6.0.3
Requires-Dist: typer>=0.9.0
